flamingpy/__init__.py
flamingpy/_version.py
flamingpy/simulations.py
flamingpy/benchmarks/decoding.py
flamingpy/benchmarks/lemon.py
flamingpy/benchmarks/matching.py
flamingpy/benchmarks/shortest_path.py
flamingpy/codes/__init__.py
flamingpy/codes/stabilizer.py
flamingpy/codes/surface_code.py
flamingpy/codes/graphs/__init__.py
flamingpy/codes/graphs/egraph.py
flamingpy/codes/graphs/stabilizer_graph.py
flamingpy/cpp/lemonpy.cp38-win_amd64.pyd
flamingpy/cv/__init__.py
flamingpy/cv/gkp.py
flamingpy/cv/ops.py
flamingpy/decoders/__init__.py
flamingpy/decoders/decoder.py
flamingpy/decoders/mwpm/__init__.py
flamingpy/decoders/mwpm/algos.py
flamingpy/decoders/mwpm/lemon.py
flamingpy/decoders/mwpm/matching.py
flamingpy/decoders/unionfind/__init__.py
flamingpy/decoders/unionfind/algos.py
flamingpy/decoders/unionfind/uf_classes.py
flamingpy/examples/decoding.py
flamingpy/examples/gkp.py
flamingpy/examples/graphstates.py
flamingpy/examples/lc_equivalence.py
flamingpy/examples/macro_reduce.py
flamingpy/examples/surface_code.py
flamingpy/noise/__init__.py
flamingpy/noise/cv.py
flamingpy/noise/iid.py
flamingpy/test_data/test_raw.csv
flamingpy/utils/__init__.py
flamingpy/utils/graph_states.py
flamingpy/utils/linalg.py
flamingpy/utils/viz.py
flamingpy-0.10.1b1.dist-info/LICENSE
flamingpy-0.10.1b1.dist-info/METADATA
flamingpy-0.10.1b1.dist-info/WHEEL
flamingpy-0.10.1b1.dist-info/top_level.txt
flamingpy-0.10.1b1.dist-info/RECORD
