Metadata-Version: 2.1
Name: flamingpy
Version: 0.10.1b1
Summary: FlamingPy is a cross-platform Python library with a variety of backends for efficient simulations of error correction in fault-tolerant quantum computers.
Home-page: https://github.com/XanaduAI/flamingpy
License: Apache License 2.0
Classifier: Development Status :: 4 - Beta
Classifier: Intended Audience :: Science/Research
Classifier: License :: OSI Approved :: Apache Software License
Classifier: Natural Language :: English
Classifier: Operating System :: POSIX
Classifier: Operating System :: MacOS :: MacOS X
Classifier: Operating System :: POSIX :: Linux
Classifier: Operating System :: Microsoft :: Windows
Classifier: Programming Language :: Python
Classifier: Programming Language :: Python :: 3
Classifier: Programming Language :: Python :: 3.8
Classifier: Programming Language :: Python :: 3.9
Classifier: Programming Language :: Python :: 3.10
Classifier: Programming Language :: Python :: 3 :: Only
Classifier: Topic :: Scientific/Engineering :: Physics
Requires-Python: >=3.8,!=3.11.*
License-File: LICENSE
Requires-Dist: matplotlib (>=3.3.3)
Requires-Dist: networkx (>=2.5)
Requires-Dist: numpy (>=1.21)
Requires-Dist: pandas (>=1.2.1)
Requires-Dist: retworkx (>=0.10.2)
Requires-Dist: scipy (>=1.6)
Requires-Dist: thewalrus (>=0.19.0)
